{
  "type": "minecraft:block",
  "random_sequence": "better_on_bedrock:blocks/pink_lavender",
  "pools": [
    {
      "bonus_rolls": 0.0,
      "rolls": 1.0,
      "entries": [
        {
          "type": "minecraft:item",
          "name": "better_on_bedrock:pink_lavender",
          "conditions": [
            {
              "block": "better_on_bedrock:pink_lavender",
              "condition": "minecraft:block_state_property"
            }
          ]
        }
      ],
      "conditions": [
        { "condition": "minecraft:survives_explosion" }
      ]
    }
  ]
}